native/romi/_init_robotpy_native_romi.py
native/romi/robotpy-native-romi.pc
native/romi/include/frc/romi/OnBoardIO.h
native/romi/include/frc/romi/RomiGyro.h
native/romi/include/frc/romi/RomiMotor.h
native/romi/lib/libromiVendordep.so
robotpy_native_romi-2026.2.1.dist-info/METADATA
robotpy_native_romi-2026.2.1.dist-info/WHEEL
robotpy_native_romi-2026.2.1.dist-info/entry_points.txt
robotpy_native_romi-2026.2.1.dist-info/RECORD
