Metadata-Version: 2.4
Name: robotpy-native-romi
Version: 2026.2.1
Summary: WPILib Romi support library
License-Expression: BSD-3-Clause
Requires-Dist: robotpy-native-wpilib==2026.2.1
